{
    "Name": "wf pixie apricot",
    "Description": "...",
    "TranslationKey": "pixie-apricot",
    "Category": "Fruit",
    "Edibility": 25,
    "Price": 200,
    "IsColored": false,
    "EdibleIsDrink": false,
    "EdibleBuffs": {
                    "Farming": 0,
                    "Fishing": 0,
                    "Mining": 0,
                    "Luck": 0,
                    "Foraging": 0,
                    "MaxStamina": 30,
                    "MagnetRadius": 0,
                    "Speed": 0,
                    "Defense": 0, 
                    "Attack": 0,
                    "Duration": 360, // 360 seconds (aka 6 min)
                      },
    "GiftTastes":
    {
        "Love": ["Emily","Dwarf", "Krobus", "Wizard"],

    },
    "ContextTags": [
        "season_spring",
        "fruit_tree_item",
        "pixie_fruit",
        "color_salmon"
    ]
}
