{
    "Name": "wf berry kombucha",
    "Description": "...",
    "TranslationKey":"berry-kombucha",
    "Category": "ArtisanGoods",
    "Edibility": 10,
    "EdibleIsDrink": true,
    "EdibleBuffs": null,
    "Price": 250,
    "GiftTastes":
    {
		"Love": ["Abigail","Alex","Caroline","Emily","Harvey","Haley","Leah"],
		"Like": ["Dwarf", "Elliott", "Gus","Lewis","Linus","Maru","Sandy","Jodi","Kent"],
		"Neutral": ["Clint","Evelyn","Marnie","Pierre","Krobus","Shane","Wizard","Robin"],
		"Dislike ": ["George","Sam","Sebastian","Penny"],
		"Hate": ["Jas","Leo","Pam","Vincent","Willy"]
    },
    "Recipe": null,
    "CanPurchase": false,       
    
	"ContextTags":
        [
		"wildflour_kombucha",
		"kombucha_item",
    "drink_item",
		"color_pink"
		],
}